versie/__init__.py
versie/cli.py
versie-0.0.2.dist-info/METADATA
versie-0.0.2.dist-info/WHEEL
versie-0.0.2.dist-info/entry_points.txt
versie-0.0.2.dist-info/top_level.txt
versie-0.0.2.dist-info/RECORD
